pytreegrav/__init__.py
pytreegrav/bruteforce.py
pytreegrav/dynamic_tree.py
pytreegrav/frontend.py
pytreegrav/kernel.py
pytreegrav/misc.py
pytreegrav/octree.py
pytreegrav/treewalk.py
pytreegrav/treewalk2.py
pytreegrav-1.1.3.dist-info/LICENSE.txt
pytreegrav-1.1.3.dist-info/METADATA
pytreegrav-1.1.3.dist-info/WHEEL
pytreegrav-1.1.3.dist-info/top_level.txt
pytreegrav-1.1.3.dist-info/RECORD
