Metadata-Version: 2.1
Name: pytreegrav
Version: 1.1.3
Summary: Fast approximate gravitational force and potential calculations
Author: Mike Grudic
Author-email: mike.grudich@gmail.com
Project-URL: Bug Tracker, https://github.com/mikegrudic/pytreegrav
Classifier: Programming Language :: Python :: 3
Classifier: License :: OSI Approved :: MIT License
Classifier: Operating System :: OS Independent
Requires-Python: >=3.6
License-File: LICENSE.txt
Requires-Dist: numba
Requires-Dist: numpy
Requires-Dist: scipy
